hbctool/__init__.py
hbctool/hasm.py
hbctool/hbc/__init__.py
hbctool/hbc/hbc59/.DS_Store
hbctool/hbc/hbc59/__init__.py
hbctool/hbc/hbc59/data/opcode.json
hbctool/hbc/hbc59/data/structure.json
hbctool/hbc/hbc59/example/index.android.bundle
hbctool/hbc/hbc59/example/pretty.out
hbctool/hbc/hbc59/example/raw.out
hbctool/hbc/hbc59/parser.py
hbctool/hbc/hbc59/raw/BytecodeFileFormat.h
hbctool/hbc/hbc59/raw/BytecodeList.def
hbctool/hbc/hbc59/raw/SerializedLiteralGenerator.h
hbctool/hbc/hbc59/test.py
hbctool/hbc/hbc59/tool/opcode_generator.py
hbctool/hbc/hbc59/translator.py
hbctool/hbc/hbc62/.DS_Store
hbctool/hbc/hbc62/__init__.py
hbctool/hbc/hbc62/data/opcode.json
hbctool/hbc/hbc62/data/structure.json
hbctool/hbc/hbc62/example/index.android.bundle
hbctool/hbc/hbc62/example/pretty.out
hbctool/hbc/hbc62/example/raw.out
hbctool/hbc/hbc62/parser.py
hbctool/hbc/hbc62/raw/BytecodeFileFormat.h
hbctool/hbc/hbc62/raw/BytecodeList.def
hbctool/hbc/hbc62/raw/SerializedLiteralGenerator.h
hbctool/hbc/hbc62/test.py
hbctool/hbc/hbc62/tool/opcode_generator.py
hbctool/hbc/hbc62/translator.py
hbctool/hbc/hbc74/__init__.py
hbctool/hbc/hbc74/data/opcode.json
hbctool/hbc/hbc74/data/structure.json
hbctool/hbc/hbc74/example/index.android.bundle
hbctool/hbc/hbc74/example/objdump.out
hbctool/hbc/hbc74/example/pretty.out
hbctool/hbc/hbc74/example/raw.out
hbctool/hbc/hbc74/parser.py
hbctool/hbc/hbc74/raw/BytecodeFileFormat.h
hbctool/hbc/hbc74/raw/BytecodeList.def
hbctool/hbc/hbc74/raw/SerializedLiteralGenerator.h
hbctool/hbc/hbc74/test.py
hbctool/hbc/hbc74/tool/opcode_generator.py
hbctool/hbc/hbc74/translator.py
hbctool/hbc/hbc76/__init__.py
hbctool/hbc/hbc76/data/opcode.json
hbctool/hbc/hbc76/data/structure.json
hbctool/hbc/hbc76/example/index.android.bundle
hbctool/hbc/hbc76/example/objdump.out
hbctool/hbc/hbc76/example/pretty.out
hbctool/hbc/hbc76/example/raw.out
hbctool/hbc/hbc76/parser.py
hbctool/hbc/hbc76/raw/BytecodeFileFormat.h
hbctool/hbc/hbc76/raw/BytecodeList.def
hbctool-0.1.5.dist-info/entry_points.txt
hbctool-0.1.5.dist-info/LICENSE
hbctool-0.1.5.dist-info/WHEEL
hbctool-0.1.5.dist-info/METADATA
hbctool-0.1.5.dist-info/RECORD
