Metadata-Version: 2.1
Name: hbctool
Version: 0.1.5
Summary: A command-line interface for disassembling and assembling the Hermes Bytecode.
Home-page: https://github.com/bongtrop/hbctool
License: MIT
Keywords: hbc,hermes,bytecode,reverse,hacking
Author: bongtrop
Requires-Python: >=3.6,<4.0
Classifier: Development Status :: 3 - Alpha
Classifier: License :: OSI Approved :: MIT License
Classifier: Natural Language :: English
Classifier: Programming Language :: Python
Classifier: Programming Language :: Python :: 3
Classifier: Programming Language :: Python :: 3.6
Classifier: Programming Language :: Python :: 3.7
Classifier: Programming Language :: Python :: 3.8
Classifier: Programming Language :: Python :: 3.9
Requires-Dist: docopt (>=0.6.2,<0.7.0)
Project-URL: Documentation, https://github.com/bongtrop/hbctool
Project-URL: Repository, https://github.com/bongtrop/hbctool
